pyssgen/__init__.py
pyssgen/__main__.py
pyssgen-1.1.0.dist-info/LICENCE
pyssgen-1.1.0.dist-info/METADATA
pyssgen-1.1.0.dist-info/WHEEL
pyssgen-1.1.0.dist-info/top_level.txt
pyssgen-1.1.0.dist-info/RECORD
