Metadata-Version: 2.1
Name: pyssgen
Version: 1.1.0
Summary: Static site generator built with python
Home-page: https://github.com/ken-soares/pyssgen
Author: Kenneth Soares
Author-email: kensoares@gmail.com
Classifier: Programming Language :: Python :: 3
Classifier: License :: OSI Approved :: MIT License
Classifier: Operating System :: OS Independent
License-File: LICENCE
Requires-Dist: jinja2
Requires-Dist: requests
Requires-Dist: markdown
Requires-Dist: markupsafe
Requires-Dist: python-frontmatter
Requires-Dist: python-slugify
Requires-Dist: pyyaml
Requires-Dist: text-unidecode
